<?xml version="1.0" encoding="UTF-8"?>
<objects serializationModel="Studio.02.02.00">
	<object class="AudioFile" id="{943572e2-c767-4729-8db6-c150a0acbcd8}">
		<property name="assetPath">
			<value>Units/FLAKT/iflamob.wav</value>
		</property>
		<property name="frequencyInKHz">
			<value>22.0499992</value>
		</property>
		<property name="channelCount">
			<value>1</value>
		</property>
		<property name="length">
			<value>0.87197278911564624</value>
		</property>
		<relationship name="masterAssetFolder">
			<destination>{f8f660be-cea2-4f2a-94d8-0a35db52223b}</destination>
		</relationship>
	</object>
</objects>
