<?xml version="1.0" encoding="UTF-8"?>
<objects serializationModel="Studio.02.02.00">
	<object class="AudioFile" id="{982e3288-1c05-4ab7-842c-79a702e4f860}">
		<property name="assetPath">
			<value>Units/ENG/2/ienyfea.wav</value>
		</property>
		<property name="frequencyInKHz">
			<value>22.0499992</value>
		</property>
		<property name="channelCount">
			<value>1</value>
		</property>
		<property name="length">
			<value>1.1991836734693877</value>
		</property>
		<relationship name="masterAssetFolder">
			<destination>{f8f660be-cea2-4f2a-94d8-0a35db52223b}</destination>
		</relationship>
	</object>
</objects>
