<?xml version="1.0" encoding="UTF-8"?>
<objects serializationModel="Studio.02.02.00">
	<object class="AudioFile" id="{e15d622c-e102-4286-a207-3dd956ab1f42}">
		<property name="assetPath">
			<value>Units/JJT/vztdi (5).wav</value>
		</property>
		<property name="frequencyInKHz">
			<value>48</value>
		</property>
		<property name="channelCount">
			<value>1</value>
		</property>
		<property name="length">
			<value>0.83733333333333337</value>
		</property>
		<relationship name="masterAssetFolder">
			<destination>{f8f660be-cea2-4f2a-94d8-0a35db52223b}</destination>
		</relationship>
	</object>
</objects>
